lzokay-2.1.0.dist-info/METADATA
lzokay-2.1.0.dist-info/WHEEL
lzokay-2.1.0.dist-info/licenses/LICENSE
lzokay/__init__.py
lzokay/__init__.pyi
lzokay/lzokay.abi3.so
lzokay/py.typed
lzokay-2.1.0.dist-info/RECORD
