Metadata-Version: 2.4
Name: lzokay
Version: 2.1.0
Classifier: Development Status :: 5 - Production/Stable
Classifier: Intended Audience :: Developers
Classifier: Programming Language :: Rust
Requires-Dist: pytest ; extra == 'test'
Provides-Extra: test
License-File: LICENSE
Summary: Python bindings for LZ👌, a LZO compression/decompression algorithm.
Author-email: Luke Street <luke@street.dev>, Henrique Gemignani <henrique@gemignani.org>
License-Expression: MIT
Requires-Python: >=3.10
Project-URL: Homepage, https://github.com/encounter/lzokay-rs
